{"purchase1": {"customer_name": "kepo nian", "product_name": "Oppo f1", "amount": "2", "address": "Jln Dr M.Isa", "transact_date": "20 April 2021", "product_price": "1.2 Juta IDR", "retailer_name": "Indo Cell"}, "purchase3": {"customer_name": "budi01", "product_name": "baseng", "amount": "baseng", "address": "bseng", "transact_date": "baseng", "product_price": "baseng", "retailer_name": "baseng"}, "purchase4": {"customer_name": "omke_ngab", "product_name": "55", "amount": "66", "address": "77", "transact_date": "omke", "product_price": "kemren", "retailer_name": "ngabers"}}